LICENSE
README.md
setup.py
ark_mainsail.egg-info/PKG-INFO
ark_mainsail.egg-info/SOURCES.txt
ark_mainsail.egg-info/dependency_links.txt
ark_mainsail.egg-info/entry_points.txt
ark_mainsail.egg-info/requires.txt
ark_mainsail.egg-info/top_level.txt
mainsail/__init__.py
mainsail/config.py
mainsail/deserializer.py
mainsail/identity.py
mainsail/rest.py
mainsail/serializer.py
mainsail/transaction.py
mainsail/webhook.py
mainsail/tx/__init__.py
mainsail/tx/v1.py
mnsl_pool/__init__.py
mnsl_pool/__main__.py
mnsl_pool/api.py
mnsl_pool/biom.py
mnsl_pool/tbw.py
test/__init__.py
test/test_identity.py
test/test_v1_builders.py