Metadata-Version: 2.1
Name: ark-mainsail
Version: 1.2.1
Summary: Interact with ARK blockchain trough mainsail framework
Home-page: https://github.com/Moustikitos/python-mainsail
Author: Toons
Author-email: moustikitos@gmail.com
Maintainer: Toons
Maintainer-email: moustikitos@gmail.com
License: Copyright 2024, MIT licence
Project-URL: Bug Reports, https://github.com/Moustikitos/python-mainsail/issues
Project-URL: Funding, https://github.com/Moustikitos/python-mainsail?tab=readme-ov-file#support-this-project
Project-URL: Source, https://github.com/Moustikitos/python-mainsail/
Keywords: api,ark,blockchain
Classifier: Development Status :: 5 - Production/Stable
Classifier: Environment :: Console
Classifier: Environment :: Web Environment
Classifier: Intended Audience :: Developers
Classifier: Intended Audience :: End Users/Desktop
Classifier: License :: OSI Approved :: MIT License
Classifier: Operating System :: OS Independent
Classifier: Programming Language :: Python
Classifier: Programming Language :: Python :: 3
License-File: LICENSE
Requires-Dist: requests==2.31.0
Requires-Dist: base58==2.1.1
Requires-Dist: pyaes==1.6.1
Requires-Dist: blspy==2.0.3
Requires-Dist: cSecp256k1==1.1.2
